express_schema/__init__.py
express_schema/__main__.py
express_schema/_common.py
express_schema/lex.py
express_schema/main.py
express_schema/parse.py
express_schema/py.typed
express_schema-1.0.2.dist-info/licenses/LICENSE
express_schema-1.0.2.dist-info/METADATA
express_schema-1.0.2.dist-info/WHEEL
express_schema-1.0.2.dist-info/entry_points.txt
express_schema-1.0.2.dist-info/top_level.txt
express_schema-1.0.2.dist-info/RECORD
