Metadata-Version: 2.4
Name: express-schema
Version: 1.0.2
Summary: Parse EXPRESS Schema (ISO 10303-11).
Author-email: Marko Ristin <marko@ristin.ch>
Project-URL: repository, https://github.com/aas-core-works/express-schema
Classifier: Development Status :: 5 - Production/Stable
Classifier: Intended Audience :: Developers
Classifier: License :: OSI Approved :: MIT License
Classifier: Programming Language :: Python :: 3.10
Classifier: Programming Language :: Python :: 3.11
Classifier: Programming Language :: Python :: 3.12
Classifier: Programming Language :: Python :: 3.13
Requires-Python: >=3.10
License-File: LICENSE
Requires-Dist: icontract<3,>=2
Dynamic: license-file
